nui_lambda_shared_utils/__init__.py
nui_lambda_shared_utils/base_client.py
nui_lambda_shared_utils/cli.py
nui_lambda_shared_utils/cloudwatch_metrics.py
nui_lambda_shared_utils/config.py
nui_lambda_shared_utils/db_client.py
nui_lambda_shared_utils/error_handler.py
nui_lambda_shared_utils/es_client.py
nui_lambda_shared_utils/es_query_builder.py
nui_lambda_shared_utils/powertools_helpers.py
nui_lambda_shared_utils/secrets_helper.py
nui_lambda_shared_utils/slack_client.py
nui_lambda_shared_utils/slack_formatter.py
nui_lambda_shared_utils/timezone.py
nui_lambda_shared_utils/utils.py
nui_lambda_shared_utils/slack_setup/__init__.py
nui_lambda_shared_utils/slack_setup/channel_creator.py
nui_lambda_shared_utils/slack_setup/channel_definitions.py
nui_lambda_shared_utils/slack_setup/setup_helpers.py
nui_lambda_shared_utils-1.1.0.dist-info/licenses/LICENSE
nui_lambda_shared_utils-1.1.0.dist-info/METADATA
nui_lambda_shared_utils-1.1.0.dist-info/WHEEL
nui_lambda_shared_utils-1.1.0.dist-info/entry_points.txt
nui_lambda_shared_utils-1.1.0.dist-info/top_level.txt
nui_lambda_shared_utils-1.1.0.dist-info/RECORD
