Metadata-Version: 2.4
Name: nui-lambda-shared-utils
Version: 1.1.0
Summary: Enterprise-grade utilities for AWS Lambda functions with Slack, Elasticsearch, and monitoring integrations
Home-page: https://github.com/nuimarkets/nui-lambda-shared-utils
Author: NUI Markets
Author-email: NUI Markets <develop@nuimarkets.com>
Project-URL: Homepage, https://github.com/nuimarkets/nui-lambda-shared-utils
Project-URL: Bug Tracker, https://github.com/nuimarkets/nui-lambda-shared-utils/issues
Project-URL: Documentation, https://github.com/nuimarkets/nui-lambda-shared-utils/blob/main/README.md
Project-URL: Source, https://github.com/nuimarkets/nui-lambda-shared-utils
Keywords: aws,lambda,utilities,slack,elasticsearch,monitoring,serverless
Classifier: Development Status :: 4 - Beta
Classifier: Intended Audience :: Developers
Classifier: License :: OSI Approved :: MIT License
Classifier: Operating System :: OS Independent
Classifier: Programming Language :: Python :: 3
Classifier: Programming Language :: Python :: 3.9
Classifier: Programming Language :: Python :: 3.10
Classifier: Programming Language :: Python :: 3.11
Classifier: Programming Language :: Python :: 3.12
Classifier: Topic :: Software Development :: Libraries :: Python Modules
Classifier: Topic :: System :: Monitoring
Classifier: Topic :: Internet :: WWW/HTTP :: Dynamic Content
Classifier: Environment :: Console
Classifier: Framework :: AWS CDK
Requires-Python: >=3.9
License-File: LICENSE
Requires-Dist: boto3>=1.20.0
Requires-Dist: pytz>=2021.3
Requires-Dist: click>=8.0.0
Requires-Dist: pyyaml>=6.0
Provides-Extra: elasticsearch
Requires-Dist: elasticsearch<8.0.0,>=7.17.0; extra == "elasticsearch"
Provides-Extra: database
Requires-Dist: pymysql>=1.0.0; extra == "database"
Requires-Dist: psycopg2-binary>=2.9.0; extra == "database"
Provides-Extra: slack
Requires-Dist: slack-sdk>=3.19.0; extra == "slack"
Provides-Extra: powertools
Requires-Dist: aws-lambda-powertools<4.0.0,>=3.6.0; extra == "powertools"
Requires-Dist: coloredlogs>=15.0; extra == "powertools"
Provides-Extra: all
Requires-Dist: elasticsearch<8.0.0,>=7.17.0; extra == "all"
Requires-Dist: pymysql>=1.0.0; extra == "all"
Requires-Dist: psycopg2-binary>=2.9.0; extra == "all"
Requires-Dist: slack-sdk>=3.19.0; extra == "all"
Requires-Dist: aws-lambda-powertools<4.0.0,>=3.6.0; extra == "all"
Requires-Dist: coloredlogs>=15.0; extra == "all"
Provides-Extra: dev
Requires-Dist: pytest>=7.0.0; extra == "dev"
Requires-Dist: pytest-cov>=4.0.0; extra == "dev"
Requires-Dist: pytest-mock>=3.10.0; extra == "dev"
Requires-Dist: moto>=4.0.0; extra == "dev"
Requires-Dist: black>=22.0.0; extra == "dev"
Requires-Dist: mypy>=0.990; extra == "dev"
Requires-Dist: boto3-stubs[essential]>=1.20.0; extra == "dev"
Requires-Dist: twine>=4.0.0; extra == "dev"
Requires-Dist: build>=0.8.0; extra == "dev"
Dynamic: author
Dynamic: home-page
Dynamic: license-file
Dynamic: requires-python
